synthid_text/detector_bayesian.py
synthid_text/detector_mean.py
synthid_text/g_value_expectations.py
synthid_text/hashing_function.py
synthid_text/logits_processing.py
synthid_text/logits_processing_test.py
synthid_text/synthid_mixin.py
synthid_text/synthid_mixin_test.py
synthid_text/torch_testing.py
synthid_text-0.2.1.dist-info/LICENSE
synthid_text-0.2.1.dist-info/METADATA
synthid_text-0.2.1.dist-info/WHEEL
synthid_text-0.2.1.dist-info/top_level.txt
synthid_text-0.2.1.dist-info/RECORD
