Metadata-Version: 2.1
Name: synthid-text
Version: 0.2.1
Summary: SynthID Text: Identifying AI-generated text content
Author: DeepMind Technologies Limited
License: 
Project-URL: Homepage, https://deepmind.google/technologies/synthid/
Project-URL: Repository, https://github.com/google-deepmind/synthid-text
Project-URL: Bug Tracker, https://github.com/google-deepmind/synthid-text/issues
Project-URL: Demo, https://colab.research.google.com/github/google-deepmind/synthid-text/blob/main/notebooks/synthid_text_huggingface_integration.ipynb
Keywords: artificial intelligence,language models,machine learning,text generation,watermarking
Classifier: Development Status :: 4 - Beta
Classifier: Framework :: Pytest
Classifier: Intended Audience :: Developers
Classifier: Intended Audience :: Science/Research
Classifier: License :: OSI Approved :: Apache Software License
Classifier: Operating System :: OS Independent
Classifier: Programming Language :: Python :: 3 :: Only
Classifier: Programming Language :: Python :: 3.10
Classifier: Programming Language :: Python :: 3.11
Classifier: Topic :: Scientific/Engineering :: Artificial Intelligence
Classifier: Typing :: Typed
Requires-Python: >=3.9
License-File: LICENSE
Requires-Dist: flax
Requires-Dist: immutabledict ==4.2.0
Requires-Dist: jax[cuda]
Requires-Dist: jaxtyping
Requires-Dist: numpy ==1.26.0
Requires-Dist: optax
Requires-Dist: scikit-learn
Requires-Dist: torch ==2.4.0
Requires-Dist: tqdm
Requires-Dist: transformers ==4.43.3
Provides-Extra: notebook
Requires-Dist: datasets ; extra == 'notebook'
Requires-Dist: huggingface-hub ; extra == 'notebook'
Requires-Dist: ipywidgets ; extra == 'notebook'
Requires-Dist: pandas ; extra == 'notebook'
Requires-Dist: tensorflow ; extra == 'notebook'
Provides-Extra: notebook-local
Requires-Dist: synthid-text[notebook] ; extra == 'notebook-local'
Requires-Dist: notebook ; extra == 'notebook-local'
Provides-Extra: test
Requires-Dist: absl-py ; extra == 'test'
Requires-Dist: mock ; extra == 'test'
Requires-Dist: pytest ; extra == 'test'
